setup.py
emacsipython/__init__.py
emacsipython.egg-info/PKG-INFO
emacsipython.egg-info/SOURCES.txt
emacsipython.egg-info/dependency_links.txt
emacsipython.egg-info/not-zip-safe
emacsipython.egg-info/top_level.txt