Metadata-Version: 1.0
Name: emacsipython
Version: 0.1.0
Summary: Utility function for calling an IPython embed that works in Emacs.
Home-page: UNKNOWN
Author: Nathan Addy
Author-email: nathan.addy@windfalltechnical.com
License: MIT
Platform: UNKNOWN
